[
  {
    "inputs": [
      {
        "internalType": "address",
        "name": "_prizePool",
        "type": "address"
      },
      {
        "internalType": "address",
        "name": "_ultibetsTreasury",
        "type": "address"
      },
      {
        "internalType": "address",
        "name": "_ultibetsBuyBack",
        "type": "address"
      }
    ],
    "stateMutability": "nonpayable",
    "type": "constructor"
  },
  {
    "anonymous": false,
    "inputs": [
      {
        "indexed": false,
        "internalType": "uint256",
        "name": "eventID",
        "type": "uint256"
      }
    ],
    "name": "EventCreated",
    "type": "event"
  },
  {
    "anonymous": false,
    "inputs": [
      {
        "indexed": true,
        "internalType": "address",
        "name": "previousOwner",
        "type": "address"
      },
      {
        "indexed": true,
        "internalType": "address",
        "name": "newOwner",
        "type": "address"
      }
    ],
    "name": "OwnershipTransferred",
    "type": "event"
  },
  {
    "anonymous": false,
    "inputs": [
      {
        "indexed": false,
        "internalType": "uint256",
        "name": "eventID",
        "type": "uint256"
      }
    ],
    "name": "PickEventWinner",
    "type": "event"
  },
  {
    "anonymous": false,
    "inputs": [
      {
        "indexed": false,
        "internalType": "address",
        "name": "bettor",
        "type": "address"
      },
      {
        "indexed": false,
        "internalType": "uint256",
        "name": "eventID",
        "type": "uint256"
      },
      {
        "indexed": false,
        "internalType": "uint8",
        "name": "roundLevel",
        "type": "uint8"
      },
      {
        "indexed": false,
        "internalType": "enum SBCRoundsCore.RoundResult",
        "name": "result",
        "type": "uint8"
      }
    ],
    "name": "PredictionPlaced",
    "type": "event"
  },
  {
    "anonymous": false,
    "inputs": [
      {
        "indexed": false,
        "internalType": "address",
        "name": "bettor",
        "type": "address"
      },
      {
        "indexed": false,
        "internalType": "uint256",
        "name": "eventID",
        "type": "uint256"
      }
    ],
    "name": "RefundCanceledRound",
    "type": "event"
  },
  {
    "anonymous": false,
    "inputs": [
      {
        "indexed": false,
        "internalType": "address",
        "name": "",
        "type": "address"
      },
      {
        "indexed": false,
        "internalType": "uint256",
        "name": "eventID",
        "type": "uint256"
      }
    ],
    "name": "Register",
    "type": "event"
  },
  {
    "anonymous": false,
    "inputs": [
      {
        "indexed": false,
        "internalType": "uint256",
        "name": "eventID",
        "type": "uint256"
      },
      {
        "indexed": false,
        "internalType": "enum SBCRoundsCore.EventState",
        "name": "state",
        "type": "uint8"
      },
      {
        "indexed": false,
        "internalType": "uint256",
        "name": "prizeAmount",
        "type": "uint256"
      },
      {
        "indexed": false,
        "internalType": "enum SBCRoundsCore.VotingResult",
        "name": "voteResult",
        "type": "uint8"
      },
      {
        "indexed": false,
        "internalType": "uint16",
        "name": "winnerNumber",
        "type": "uint16"
      }
    ],
    "name": "ReportVoteResult",
    "type": "event"
  },
  {
    "anonymous": false,
    "inputs": [
      {
        "indexed": false,
        "internalType": "uint256",
        "name": "eventID",
        "type": "uint256"
      },
      {
        "indexed": false,
        "internalType": "uint8",
        "name": "roundLevel",
        "type": "uint8"
      },
      {
        "indexed": false,
        "internalType": "uint16",
        "name": "playersNumber",
        "type": "uint16"
      },
      {
        "indexed": false,
        "internalType": "string",
        "name": "description",
        "type": "string"
      },
      {
        "indexed": false,
        "internalType": "uint256",
        "name": "startTime",
        "type": "uint256"
      }
    ],
    "name": "RoundAdded",
    "type": "event"
  },
  {
    "anonymous": false,
    "inputs": [
      {
        "indexed": false,
        "internalType": "uint256",
        "name": "eventID",
        "type": "uint256"
      },
      {
        "indexed": false,
        "internalType": "uint8",
        "name": "roundLevel",
        "type": "uint8"
      }
    ],
    "name": "RoundCanceled",
    "type": "event"
  },
  {
    "anonymous": false,
    "inputs": [
      {
        "indexed": false,
        "internalType": "uint256",
        "name": "eventID",
        "type": "uint256"
      },
      {
        "indexed": false,
        "internalType": "uint8",
        "name": "roundLevel",
        "type": "uint8"
      }
    ],
    "name": "RoundFinished",
    "type": "event"
  },
  {
    "anonymous": false,
    "inputs": [
      {
        "indexed": false,
        "internalType": "uint256",
        "name": "eventID",
        "type": "uint256"
      },
      {
        "indexed": false,
        "internalType": "uint8",
        "name": "roundLevel",
        "type": "uint8"
      },
      {
        "indexed": false,
        "internalType": "string",
        "name": "description",
        "type": "string"
      },
      {
        "indexed": false,
        "internalType": "uint256",
        "name": "startTime",
        "type": "uint256"
      }
    ],
    "name": "RoundUpdated",
    "type": "event"
  },
  {
    "anonymous": false,
    "inputs": [
      {
        "indexed": false,
        "internalType": "uint256",
        "name": "eventID",
        "type": "uint256"
      },
      {
        "indexed": false,
        "internalType": "uint8",
        "name": "totalRound",
        "type": "uint8"
      }
    ],
    "name": "UpdateTotalRound",
    "type": "event"
  },
  {
    "anonymous": false,
    "inputs": [
      {
        "indexed": false,
        "internalType": "address",
        "name": "voter",
        "type": "address"
      },
      {
        "indexed": false,
        "internalType": "uint256",
        "name": "eventID",
        "type": "uint256"
      },
      {
        "indexed": false,
        "internalType": "enum SBCRoundsCore.VotingResult",
        "name": "voteResult",
        "type": "uint8"
      }
    ],
    "name": "VoteEvent",
    "type": "event"
  },
  {
    "anonymous": false,
    "inputs": [
      {
        "indexed": false,
        "internalType": "uint256",
        "name": "eventID",
        "type": "uint256"
      },
      {
        "indexed": false,
        "internalType": "enum SBCRoundsCore.EventState",
        "name": "state",
        "type": "uint8"
      },
      {
        "indexed": false,
        "internalType": "uint16",
        "name": "claimedNumber",
        "type": "uint16"
      }
    ],
    "name": "WinnerClaimedPrize",
    "type": "event"
  },
  {
    "inputs": [
      {
        "internalType": "address",
        "name": "_admin",
        "type": "address"
      }
    ],
    "name": "addAdmin",
    "outputs": [],
    "stateMutability": "nonpayable",
    "type": "function"
  },
  {
    "inputs": [
      {
        "internalType": "address",
        "name": "_oracle",
        "type": "address"
      }
    ],
    "name": "addOracle",
    "outputs": [],
    "stateMutability": "nonpayable",
    "type": "function"
  },
  {
    "inputs": [
      {
        "internalType": "uint256",
        "name": "_eventID",
        "type": "uint256"
      },
      {
        "internalType": "string",
        "name": "_desc",
        "type": "string"
      },
      {
        "internalType": "uint256",
        "name": "_startTime",
        "type": "uint256"
      }
    ],
    "name": "addRound",
    "outputs": [],
    "stateMutability": "nonpayable",
    "type": "function"
  },
  {
    "inputs": [
      {
        "internalType": "address",
        "name": "",
        "type": "address"
      },
      {
        "internalType": "uint256",
        "name": "",
        "type": "uint256"
      },
      {
        "internalType": "uint8",
        "name": "",
        "type": "uint8"
      }
    ],
    "name": "bettorDecisionOnRound",
    "outputs": [
      {
        "internalType": "enum SBCRoundsCore.RoundResult",
        "name": "",
        "type": "uint8"
      }
    ],
    "stateMutability": "view",
    "type": "function"
  },
  {
    "inputs": [
      {
        "internalType": "uint256",
        "name": "_eventID",
        "type": "uint256"
      },
      {
        "internalType": "uint8",
        "name": "_roundLevel",
        "type": "uint8"
      },
      {
        "internalType": "uint256",
        "name": "_deadline",
        "type": "uint256"
      }
    ],
    "name": "cancelRound",
    "outputs": [],
    "stateMutability": "nonpayable",
    "type": "function"
  },
  {
    "inputs": [
      {
        "internalType": "uint256",
        "name": "_eventID",
        "type": "uint256"
      }
    ],
    "name": "claimBetCanceledRound",
    "outputs": [],
    "stateMutability": "nonpayable",
    "type": "function"
  },
  {
    "inputs": [
      {
        "internalType": "uint256",
        "name": "",
        "type": "uint256"
      }
    ],
    "name": "claimedWinnerNumberOfEvent",
    "outputs": [
      {
        "internalType": "uint16",
        "name": "",
        "type": "uint16"
      }
    ],
    "stateMutability": "view",
    "type": "function"
  },
  {
    "inputs": [],
    "name": "claimerContract",
    "outputs": [
      {
        "internalType": "contract ISBCNFTClaimer",
        "name": "",
        "type": "address"
      }
    ],
    "stateMutability": "view",
    "type": "function"
  },
  {
    "inputs": [
      {
        "internalType": "string",
        "name": "_desc",
        "type": "string"
      },
      {
        "internalType": "uint16",
        "name": "_maxPlayers",
        "type": "uint16"
      },
      {
        "internalType": "uint256",
        "name": "_registerAmount",
        "type": "uint256"
      },
      {
        "internalType": "uint256",
        "name": "_registerDeadline",
        "type": "uint256"
      },
      {
        "internalType": "uint8",
        "name": "_totalRound",
        "type": "uint8"
      },
      {
        "internalType": "uint256",
        "name": "_roundAmount",
        "type": "uint256"
      },
      {
        "internalType": "uint8",
        "name": "_orgFeePercent",
        "type": "uint8"
      }
    ],
    "name": "createNewEvent",
    "outputs": [],
    "stateMutability": "nonpayable",
    "type": "function"
  },
  {
    "inputs": [
      {
        "internalType": "uint256",
        "name": "",
        "type": "uint256"
      },
      {
        "internalType": "uint8",
        "name": "",
        "type": "uint8"
      }
    ],
    "name": "deadlineOfCancelRound",
    "outputs": [
      {
        "internalType": "uint256",
        "name": "",
        "type": "uint256"
      }
    ],
    "stateMutability": "view",
    "type": "function"
  },
  {
    "inputs": [
      {
        "internalType": "uint256",
        "name": "",
        "type": "uint256"
      }
    ],
    "name": "eventData",
    "outputs": [
      {
        "internalType": "uint256",
        "name": "eventID",
        "type": "uint256"
      },
      {
        "internalType": "string",
        "name": "description",
        "type": "string"
      },
      {
        "internalType": "uint8",
        "name": "currentLevel",
        "type": "uint8"
      },
      {
        "internalType": "uint256",
        "name": "totalAmount",
        "type": "uint256"
      },
      {
        "internalType": "uint16",
        "name": "maxPlayers",
        "type": "uint16"
      },
      {
        "internalType": "uint16",
        "name": "totalPlayers",
        "type": "uint16"
      },
      {
        "internalType": "uint256",
        "name": "registerAmount",
        "type": "uint256"
      },
      {
        "internalType": "uint256",
        "name": "roundBetAmount",
        "type": "uint256"
      },
      {
        "internalType": "uint8",
        "name": "orgFeePercent",
        "type": "uint8"
      },
      {
        "internalType": "uint8",
        "name": "totalRound",
        "type": "uint8"
      },
      {
        "internalType": "uint256",
        "name": "registerDeadline",
        "type": "uint256"
      },
      {
        "internalType": "enum SBCRoundsCore.EventState",
        "name": "state",
        "type": "uint8"
      },
      {
        "internalType": "enum SBCRoundsCore.VotingResult",
        "name": "vResult",
        "type": "uint8"
      }
    ],
    "stateMutability": "view",
    "type": "function"
  },
  {
    "inputs": [
      {
        "internalType": "uint256",
        "name": "",
        "type": "uint256"
      }
    ],
    "name": "eventVote",
    "outputs": [
      {
        "internalType": "uint256",
        "name": "startTime",
        "type": "uint256"
      },
      {
        "internalType": "uint16",
        "name": "splitPoint",
        "type": "uint16"
      },
      {
        "internalType": "uint16",
        "name": "soloPoint",
        "type": "uint16"
      }
    ],
    "stateMutability": "view",
    "type": "function"
  },
  {
    "inputs": [
      {
        "internalType": "uint256",
        "name": "_eventID",
        "type": "uint256"
      }
    ],
    "name": "getFinalRoundWinnersByEvent",
    "outputs": [
      {
        "internalType": "address[]",
        "name": "",
        "type": "address[]"
      }
    ],
    "stateMutability": "view",
    "type": "function"
  },
  {
    "inputs": [
      {
        "internalType": "uint256",
        "name": "",
        "type": "uint256"
      }
    ],
    "name": "getNFTType",
    "outputs": [
      {
        "internalType": "enum ISBCNFTType.NFTType",
        "name": "",
        "type": "uint8"
      }
    ],
    "stateMutability": "view",
    "type": "function"
  },
  {
    "inputs": [
      {
        "internalType": "uint256",
        "name": "_eventID",
        "type": "uint256"
      }
    ],
    "name": "getWinnerIDs",
    "outputs": [
      {
        "internalType": "uint16[]",
        "name": "",
        "type": "uint16[]"
      }
    ],
    "stateMutability": "view",
    "type": "function"
  },
  {
    "inputs": [
      {
        "internalType": "uint256",
        "name": "_eventID",
        "type": "uint256"
      },
      {
        "internalType": "enum SBCRoundsCore.RoundResult",
        "name": "_result",
        "type": "uint8"
      }
    ],
    "name": "getWinnersNumber",
    "outputs": [
      {
        "internalType": "uint16",
        "name": "winnerNumber",
        "type": "uint16"
      }
    ],
    "stateMutability": "view",
    "type": "function"
  },
  {
    "inputs": [
      {
        "internalType": "address",
        "name": "",
        "type": "address"
      }
    ],
    "name": "isAdmin",
    "outputs": [
      {
        "internalType": "bool",
        "name": "",
        "type": "bool"
      }
    ],
    "stateMutability": "view",
    "type": "function"
  },
  {
    "inputs": [
      {
        "internalType": "address",
        "name": "_bettor",
        "type": "address"
      },
      {
        "internalType": "uint256",
        "name": "_eventID",
        "type": "uint256"
      }
    ],
    "name": "isClaimable",
    "outputs": [
      {
        "internalType": "bool",
        "name": "",
        "type": "bool"
      }
    ],
    "stateMutability": "view",
    "type": "function"
  },
  {
    "inputs": [
      {
        "internalType": "address",
        "name": "",
        "type": "address"
      }
    ],
    "name": "isOracle",
    "outputs": [
      {
        "internalType": "bool",
        "name": "",
        "type": "bool"
      }
    ],
    "stateMutability": "view",
    "type": "function"
  },
  {
    "inputs": [
      {
        "internalType": "address",
        "name": "_address",
        "type": "address"
      },
      {
        "internalType": "uint256",
        "name": "_eventID",
        "type": "uint256"
      },
      {
        "internalType": "uint8",
        "name": "_level",
        "type": "uint8"
      }
    ],
    "name": "isWinner",
    "outputs": [
      {
        "internalType": "bool",
        "name": "",
        "type": "bool"
      }
    ],
    "stateMutability": "view",
    "type": "function"
  },
  {
    "inputs": [
      {
        "internalType": "uint256",
        "name": "_eventID",
        "type": "uint256"
      }
    ],
    "name": "massRefundCancelRound",
    "outputs": [],
    "stateMutability": "nonpayable",
    "type": "function"
  },
  {
    "inputs": [],
    "name": "noticeBetTime",
    "outputs": [
      {
        "internalType": "uint16",
        "name": "",
        "type": "uint16"
      }
    ],
    "stateMutability": "view",
    "type": "function"
  },
  {
    "inputs": [],
    "name": "owner",
    "outputs": [
      {
        "internalType": "address",
        "name": "",
        "type": "address"
      }
    ],
    "stateMutability": "view",
    "type": "function"
  },
  {
    "inputs": [
      {
        "internalType": "uint256",
        "name": "_eventID",
        "type": "uint256"
      }
    ],
    "name": "pickWinner",
    "outputs": [],
    "stateMutability": "nonpayable",
    "type": "function"
  },
  {
    "inputs": [
      {
        "internalType": "uint256",
        "name": "_eventID",
        "type": "uint256"
      },
      {
        "internalType": "enum SBCRoundsCore.RoundResult",
        "name": "_result",
        "type": "uint8"
      }
    ],
    "name": "placePrediction",
    "outputs": [],
    "stateMutability": "payable",
    "type": "function"
  },
  {
    "inputs": [
      {
        "internalType": "address",
        "name": "",
        "type": "address"
      },
      {
        "internalType": "uint256",
        "name": "",
        "type": "uint256"
      }
    ],
    "name": "playersClaimReward",
    "outputs": [
      {
        "internalType": "bool",
        "name": "",
        "type": "bool"
      }
    ],
    "stateMutability": "view",
    "type": "function"
  },
  {
    "inputs": [
      {
        "internalType": "address",
        "name": "",
        "type": "address"
      },
      {
        "internalType": "uint256",
        "name": "",
        "type": "uint256"
      }
    ],
    "name": "playersVoteState",
    "outputs": [
      {
        "internalType": "bool",
        "name": "",
        "type": "bool"
      }
    ],
    "stateMutability": "view",
    "type": "function"
  },
  {
    "inputs": [
      {
        "internalType": "uint256",
        "name": "",
        "type": "uint256"
      }
    ],
    "name": "prizeOfEvent",
    "outputs": [
      {
        "internalType": "uint256",
        "name": "",
        "type": "uint256"
      }
    ],
    "stateMutability": "view",
    "type": "function"
  },
  {
    "inputs": [],
    "name": "prizePool",
    "outputs": [
      {
        "internalType": "address",
        "name": "",
        "type": "address"
      }
    ],
    "stateMutability": "view",
    "type": "function"
  },
  {
    "inputs": [
      {
        "internalType": "uint256",
        "name": "_eventID",
        "type": "uint256"
      },
      {
        "internalType": "uint256",
        "name": "_startTime",
        "type": "uint256"
      },
      {
        "internalType": "string",
        "name": "_desc",
        "type": "string"
      }
    ],
    "name": "reActiveCanceledRound",
    "outputs": [],
    "stateMutability": "nonpayable",
    "type": "function"
  },
  {
    "inputs": [
      {
        "internalType": "address",
        "name": "",
        "type": "address"
      },
      {
        "internalType": "uint256",
        "name": "",
        "type": "uint256"
      }
    ],
    "name": "registerIDOfBettor",
    "outputs": [
      {
        "internalType": "uint16",
        "name": "",
        "type": "uint16"
      }
    ],
    "stateMutability": "view",
    "type": "function"
  },
  {
    "inputs": [
      {
        "internalType": "uint256",
        "name": "_eventID",
        "type": "uint256"
      }
    ],
    "name": "registerOnEvent",
    "outputs": [],
    "stateMutability": "payable",
    "type": "function"
  },
  {
    "inputs": [],
    "name": "renounceOwnership",
    "outputs": [],
    "stateMutability": "nonpayable",
    "type": "function"
  },
  {
    "inputs": [
      {
        "internalType": "uint256",
        "name": "_eventID",
        "type": "uint256"
      },
      {
        "internalType": "enum SBCRoundsCore.RoundResult",
        "name": "_result",
        "type": "uint8"
      }
    ],
    "name": "reportResult",
    "outputs": [],
    "stateMutability": "nonpayable",
    "type": "function"
  },
  {
    "inputs": [
      {
        "internalType": "uint256",
        "name": "_eventID",
        "type": "uint256"
      }
    ],
    "name": "resultVote",
    "outputs": [],
    "stateMutability": "nonpayable",
    "type": "function"
  },
  {
    "inputs": [
      {
        "internalType": "uint256",
        "name": "",
        "type": "uint256"
      },
      {
        "internalType": "uint8",
        "name": "",
        "type": "uint8"
      }
    ],
    "name": "roundData",
    "outputs": [
      {
        "internalType": "string",
        "name": "description",
        "type": "string"
      },
      {
        "internalType": "uint256",
        "name": "eventID",
        "type": "uint256"
      },
      {
        "internalType": "uint256",
        "name": "yesPoolAmount",
        "type": "uint256"
      },
      {
        "internalType": "uint256",
        "name": "noPoolAmount",
        "type": "uint256"
      },
      {
        "internalType": "uint256",
        "name": "startTime",
        "type": "uint256"
      },
      {
        "internalType": "enum SBCRoundsCore.RoundResult",
        "name": "result",
        "type": "uint8"
      },
      {
        "internalType": "enum SBCRoundsCore.RoundState",
        "name": "state",
        "type": "uint8"
      }
    ],
    "stateMutability": "view",
    "type": "function"
  },
  {
    "inputs": [
      {
        "internalType": "contract ISBCNFTClaimer",
        "name": "_claimer",
        "type": "address"
      }
    ],
    "name": "setClaimerContract",
    "outputs": [],
    "stateMutability": "nonpayable",
    "type": "function"
  },
  {
    "inputs": [
      {
        "internalType": "uint16",
        "name": "_noticeTime",
        "type": "uint16"
      }
    ],
    "name": "setNoticeBetTime",
    "outputs": [],
    "stateMutability": "nonpayable",
    "type": "function"
  },
  {
    "inputs": [
      {
        "internalType": "address",
        "name": "_prizePool",
        "type": "address"
      }
    ],
    "name": "setPrizePool",
    "outputs": [],
    "stateMutability": "nonpayable",
    "type": "function"
  },
  {
    "inputs": [
      {
        "internalType": "address",
        "name": "_ultiBetsRandomGen",
        "type": "address"
      }
    ],
    "name": "setUltiBetsVRF",
    "outputs": [],
    "stateMutability": "nonpayable",
    "type": "function"
  },
  {
    "inputs": [
      {
        "internalType": "address",
        "name": "_BuyBack",
        "type": "address"
      }
    ],
    "name": "setUltibetsBuyBack",
    "outputs": [],
    "stateMutability": "nonpayable",
    "type": "function"
  },
  {
    "inputs": [
      {
        "internalType": "uint256",
        "name": "",
        "type": "uint256"
      }
    ],
    "name": "solorWinnerOfVote",
    "outputs": [
      {
        "internalType": "address",
        "name": "",
        "type": "address"
      }
    ],
    "stateMutability": "view",
    "type": "function"
  },
  {
    "inputs": [],
    "name": "totalEventNumber",
    "outputs": [
      {
        "internalType": "uint256",
        "name": "",
        "type": "uint256"
      }
    ],
    "stateMutability": "view",
    "type": "function"
  },
  {
    "inputs": [
      {
        "internalType": "address",
        "name": "newOwner",
        "type": "address"
      }
    ],
    "name": "transferOwnership",
    "outputs": [],
    "stateMutability": "nonpayable",
    "type": "function"
  },
  {
    "inputs": [],
    "name": "ultiBetsRandomGen",
    "outputs": [
      {
        "internalType": "address",
        "name": "",
        "type": "address"
      }
    ],
    "stateMutability": "view",
    "type": "function"
  },
  {
    "inputs": [],
    "name": "ultibetsBuyBack",
    "outputs": [
      {
        "internalType": "address",
        "name": "",
        "type": "address"
      }
    ],
    "stateMutability": "view",
    "type": "function"
  },
  {
    "inputs": [],
    "name": "ultibetsTreasury",
    "outputs": [
      {
        "internalType": "address",
        "name": "",
        "type": "address"
      }
    ],
    "stateMutability": "view",
    "type": "function"
  },
  {
    "inputs": [
      {
        "internalType": "uint256",
        "name": "_eventID",
        "type": "uint256"
      }
    ],
    "name": "unclaimCancelRoundBettorsList",
    "outputs": [
      {
        "internalType": "address[]",
        "name": "",
        "type": "address[]"
      }
    ],
    "stateMutability": "view",
    "type": "function"
  },
  {
    "inputs": [
      {
        "internalType": "uint256",
        "name": "_eventID",
        "type": "uint256"
      },
      {
        "internalType": "uint8",
        "name": "_totalRound",
        "type": "uint8"
      }
    ],
    "name": "updateEventTotalRound",
    "outputs": [],
    "stateMutability": "nonpayable",
    "type": "function"
  },
  {
    "inputs": [
      {
        "internalType": "enum SBCRoundsCore.VotingResult",
        "name": "_playerVote",
        "type": "uint8"
      },
      {
        "internalType": "uint256",
        "name": "_eventID",
        "type": "uint256"
      }
    ],
    "name": "vote",
    "outputs": [],
    "stateMutability": "nonpayable",
    "type": "function"
  },
  {
    "inputs": [],
    "name": "voteDeadline",
    "outputs": [
      {
        "internalType": "uint16",
        "name": "",
        "type": "uint16"
      }
    ],
    "stateMutability": "view",
    "type": "function"
  },
  {
    "inputs": [
      {
        "internalType": "uint256",
        "name": "_eventID",
        "type": "uint256"
      }
    ],
    "name": "winnersClaimPrize",
    "outputs": [],
    "stateMutability": "nonpayable",
    "type": "function"
  },
  {
    "inputs": [
      {
        "internalType": "uint256",
        "name": "",
        "type": "uint256"
      }
    ],
    "name": "winnersNumberOfEvent",
    "outputs": [
      {
        "internalType": "uint16",
        "name": "",
        "type": "uint16"
      }
    ],
    "stateMutability": "view",
    "type": "function"
  },
  {
    "inputs": [],
    "name": "withdrawAllFundWhenEmergency",
    "outputs": [],
    "stateMutability": "nonpayable",
    "type": "function"
  },
  {
    "stateMutability": "payable",
    "type": "receive"
  }
]